atai_gemma3_tool/__init__.py
atai_gemma3_tool/cli.py
atai_gemma3_tool/regex_filter.py
atai_gemma3_tool-0.0.3.dist-info/LICENSE
atai_gemma3_tool-0.0.3.dist-info/METADATA
atai_gemma3_tool-0.0.3.dist-info/WHEEL
atai_gemma3_tool-0.0.3.dist-info/entry_points.txt
atai_gemma3_tool-0.0.3.dist-info/top_level.txt
atai_gemma3_tool-0.0.3.dist-info/RECORD
