Metadata-Version: 2.2
Name: atai-gemma3-tool
Version: 0.0.3
Summary: CLI tool for generating text from images using the Gemma 3 model.
Home-page: https://github.com/AtomGradient/atai-gemma3-tool
Author: AtomGradient
Author-email: AtomGradient <alex@atomgradient.com>
License: MIT
Project-URL: Homepage, https://github.com/AtomGradient/atai-gemma3-tool
Project-URL: Bug Tracker, https://github.com/AtomGradient/atai-gemma3-tool/issues
Keywords: google,gemma3,image-extraction,document-processing
Classifier: Programming Language :: Python :: 3
Classifier: License :: OSI Approved :: MIT License
Classifier: Operating System :: OS Independent
Requires-Python: >=3.7
License-File: LICENSE
Requires-Dist: torch
Requires-Dist: accelerate
Requires-Dist: Pillow
Dynamic: author
Dynamic: home-page
